myassistant/__init__.py
myassistant/__main__.py
myassistant/assistant.py
myassistant-1.0.4.dist-info/LICENSE
myassistant-1.0.4.dist-info/METADATA
myassistant-1.0.4.dist-info/WHEEL
myassistant-1.0.4.dist-info/top_level.txt
myassistant-1.0.4.dist-info/RECORD
