Metadata-Version: 2.1
Name: myassistant
Version: 1.0.4
Summary: It is a assistant creater module :)
Home-page: UNKNOWN
Author: Govind Potdar
Author-email: govindpotdar2001@gmail.com
License: MIT
Platform: UNKNOWN
Classifier: License :: OSI Approved :: MIT License
Classifier: Programming Language :: Python :: 3.8
Classifier: Programming Language :: Python :: 3.9
Requires-Dist: speechrecognition
Requires-Dist: pyttsx3
Requires-Dist: datetime
Requires-Dist: psutil
Requires-Dist: wikipedia
Requires-Dist: requests
Requires-Dist: prettytable
Requires-Dist: sounddevice
Requires-Dist: wavio
Requires-Dist: scipy
